ray_helper/__init__.py
ray_helper/utils.py
ray_helper-0.3.0.dist-info/METADATA
ray_helper-0.3.0.dist-info/WHEEL
ray_helper-0.3.0.dist-info/top_level.txt
ray_helper-0.3.0.dist-info/RECORD
