Metadata-Version: 2.4
Name: ray_helper
Version: 0.3.0
Summary: A simple package to convert text to uppercase and lowercase
Requires-Python: >=3.6
Dynamic: description
Dynamic: description-content-type
Dynamic: requires-python
Dynamic: summary
